scute_client/__init__.py
scute_client/client.py
scute_client/exceptions.py
scute_client/utils.py
scute_client/apis/__init__.py
scute_client/apis/auth.py
scute_client/apis/base.py
scute_client/apis/devices.py
scute_client/apis/tokens.py
scute_client/apis/users.py
scute_client-0.1.5.dist-info/licenses/LICENSE
scute_client-0.1.5.dist-info/METADATA
scute_client-0.1.5.dist-info/WHEEL
scute_client-0.1.5.dist-info/top_level.txt
scute_client-0.1.5.dist-info/RECORD
