Metadata-Version: 2.4
Name: scute-client
Version: 0.1.5
Summary: Python client for Scute API
Author-email: Triangle Empire <dev@triangleempire.com>
License: MIT
Requires-Python: >=3.8
License-File: LICENSE
Requires-Dist: requests>=2.28.0
Dynamic: license-file
